smartseeds/__init__.py
smartseeds/decorators.py
smartseeds/dict_utils.py
smartseeds-0.2.0.dist-info/licenses/LICENSE
smartseeds-0.2.0.dist-info/METADATA
smartseeds-0.2.0.dist-info/WHEEL
smartseeds-0.2.0.dist-info/top_level.txt
smartseeds-0.2.0.dist-info/RECORD
