Metadata-Version: 2.4
Name: smartseeds
Version: 0.2.0
Summary: Essential utilities that grow smart solutions - shared utilities for the smart* ecosystem
Author-email: Genropy Team <info@genropy.org>
License: MIT
Project-URL: Homepage, https://github.com/genropy/smartseeds
Project-URL: Documentation, https://smartseeds.readthedocs.io
Project-URL: Repository, https://github.com/genropy/smartseeds
Project-URL: Bug Tracker, https://github.com/genropy/smartseeds/issues
Keywords: utilities,decorators,dict-utils,smart-ecosystem
Classifier: Development Status :: 3 - Alpha
Classifier: Intended Audience :: Developers
Classifier: License :: OSI Approved :: MIT License
Classifier: Programming Language :: Python :: 3
Classifier: Programming Language :: Python :: 3.10
Classifier: Programming Language :: Python :: 3.11
Classifier: Programming Language :: Python :: 3.12
Classifier: Topic :: Software Development :: Libraries :: Python Modules
Classifier: Topic :: Utilities
Requires-Python: >=3.10
License-File: LICENSE
Provides-Extra: dev
Requires-Dist: pytest>=7.0.0; extra == "dev"
Requires-Dist: pytest-cov>=4.0.0; extra == "dev"
Requires-Dist: ruff>=0.1.0; extra == "dev"
Requires-Dist: black>=23.0.0; extra == "dev"
Requires-Dist: mypy>=1.0.0; extra == "dev"
Provides-Extra: docs
Requires-Dist: sphinx>=8.0.0; extra == "docs"
Requires-Dist: sphinx-rtd-theme>=3.0.0; extra == "docs"
Requires-Dist: sphinx-autodoc-typehints>=3.0.0; extra == "docs"
Requires-Dist: myst-parser>=4.0.0; extra == "docs"
Requires-Dist: sphinxcontrib-mermaid>=1.0.0; extra == "docs"
Dynamic: license-file
